meowdoc/__init__.py
meowdoc/cli.py
meowdoc/core.py
meowdoc/llm.py
meowdoc/mkdocs.py
meowdoc/themes.py
meowdoc/dummy_files/hw.rs
meowdoc-0.1.0.dist-info/licenses/LICENSE
meowdoc-0.1.0.dist-info/WHEEL
meowdoc-0.1.0.dist-info/METADATA
meowdoc-0.1.0.dist-info/RECORD
