Metadata-Version: 2.4
Name: meowdoc
Version: 0.1.0
Summary: A documentation generator using Gemini and MkDocs.
Author-email: "Nafi (re-masashi)" <nafines007@gmail.com>
Requires-Python: >= 3.8
Classifier: License :: OSI Approved :: MIT License
Classifier: Programming Language :: Python :: 3.7
Classifier: Programming Language :: Python :: 3.8
Classifier: Programming Language :: Python :: 3.9
Classifier: Programming Language :: Python :: 3.10
License-File: LICENSE
Requires-Dist: python-dotenv
Requires-Dist: google-generativeai
Requires-Dist: mkdocs
Requires-Dist: toml
Requires-Dist: openai
Requires-Dist: mkdocs-material
Requires-Dist: pymdown-extensions
